pyppy/__init__.py
pyppy/args.py
pyppy/conditions.py
pyppy/config.py
pyppy/exc.py
pyppy/utils.py
test/__init__.py
test/conditions_test.py
test/config_test.py
test/fill_arguments_test.py
test/test_readme_examples.py
test/testcase.py
test/testing.py
pyppy-0.1.1.dist-info/LICENSE
pyppy-0.1.1.dist-info/METADATA
pyppy-0.1.1.dist-info/WHEEL
pyppy-0.1.1.dist-info/top_level.txt
pyppy-0.1.1.dist-info/RECORD
