Metadata-Version: 2.1
Name: pyppy
Version: 0.1.1
Summary: Python library for global configuration and conditional method execution.
Home-page: https://github.com/maehster/pyppy
Author: David Grimm
Author-email: maehster@gmail.com
License: UNKNOWN
Platform: UNKNOWN
Classifier: Programming Language :: Python :: 3
Classifier: License :: OSI Approved :: MIT License
Classifier: Operating System :: OS Independent
Requires-Python: >=3.6
Provides-Extra: dev
Requires-Dist: pytest ; extra == 'dev'
Requires-Dist: pytest-pep8 ; extra == 'dev'
Requires-Dist: pytest-cov ; extra == 'dev'
Requires-Dist: pylint (>=2.6.0) ; extra == 'dev'
